asciireqs/__init__.py
asciireqs/asciireq.py
asciireqs/asciireqexport.py
asciireqs/docparser.py
asciireqs/fields.py
asciireqs/reporting.py
asciireqs/reqdocument.py
asciireqs-0.0.9.dist-info/LICENSE
asciireqs-0.0.9.dist-info/METADATA
asciireqs-0.0.9.dist-info/WHEEL
asciireqs-0.0.9.dist-info/entry_points.txt
asciireqs-0.0.9.dist-info/top_level.txt
asciireqs-0.0.9.dist-info/RECORD
