Metadata-Version: 2.1
Name: asciireqs
Version: 0.0.9
Summary: Text-based Requirement Management using AsciiDoc and version control
Author: Helge Penne
Author-email: hpenne@gmail.com
Keywords: Requirement Management,version control,git,text-based,AsciiDoc
Classifier: Development Status :: 4 - Beta
Classifier: Intended Audience :: Developers
Classifier: Topic :: Documentation
Classifier: Topic :: Utilities
Classifier: Topic :: Text Processing :: Markup
Classifier: Topic :: Software Development :: Documentation
Classifier: License :: OSI Approved :: MIT License
Classifier: Programming Language :: Python :: 3.7
Classifier: Programming Language :: Python :: 3.8
Classifier: Programming Language :: Python :: 3.9
Classifier: Programming Language :: Python :: 3.10
Classifier: Programming Language :: Python :: 3 :: Only
Requires-Python: >=3.7, <4
License-File: LICENSE
Requires-Dist: PyYAML
Requires-Dist: openpyxl
